solanace/__init__.py
solanace/AsyncClient.py
solanace/Client.py
solanace/Jupiter.py
solanace/Metrics.py
solanace/Tokens.py
solanace/Util.py
solanace/Wallet.py
solanace-0.0.2.dist-info/LICENSE
solanace-0.0.2.dist-info/METADATA
solanace-0.0.2.dist-info/WHEEL
solanace-0.0.2.dist-info/RECORD
