Metadata-Version: 2.1
Name: solanace
Version: 0.0.2
Summary: A high-level Python library to effortlessly interact with the Solana blockchain (wip)
License: MIT
Author: Elia Hilse
Requires-Python: >=3.10,<4.0
Classifier: License :: OSI Approved :: MIT License
Classifier: Programming Language :: Python :: 3
Classifier: Programming Language :: Python :: 3.10
Classifier: Programming Language :: Python :: 3.11
Requires-Dist: solana (>=0.36.6,<0.37.0)
Requires-Dist: solders (>=0.26.0,<0.27.0)
